{
  "polls": [
    {
      "id": "1",
      "question": "What is your favorite programming language?",
      "options": [
        "JavaScript",
        "Python",
        "Java"
      ]
    },
    {
      "id": "2",
      "question": "Which is your favorite animal?",
      "options": [
        "Dog",
        "Cat",
        "Bird"
      ]
    },
    {
      "id": "3",
      "question": "What is your preferred social media platform?",
      "options": [
        "Facebook",
        "Instagram",
        "Twitter"
      ]
    },
    {
      "id": "4",
      "question": "Which is your favorite season?",
      "options": [
        "Spring",
        "Summer",
        "Autumn",
        "Winter"
      ]
    },
    {
      "id": "5",
      "question": "What is your favorite food?",
      "options": [
        "Pizza",
        "Sushi",
        "Burger"
      ]
    },
    {
      "0": {
        "name": "what is your passion ?",
        "options": [
          "Eating ",
          "Reading",
          "Watching movie",
          "Playing football"
        ]
      },
      "id": "4c20"
    },
    {
      "0": {
        "name": "hgfssgg",
        "options": [
          "dfgsdgf"
        ]
      },
      "id": "4b1b"
    },
    {
      "0": {
        "name": "xczzv",
        "options": [
          "vccv",
          "xvcxv"
        ]
      },
      "id": "7139"
    }
  ]
}